common/__init__.py
common/descryptors.py
common/errors.py
common/metaclasses.py
common/utils.py
common/variables.py
log/__init__.py
log/config_client_log.py
log/config_server_log.py
log/decorator_log.py
server/__init__.py
server/add_user.py
server/config_window.py
server/core.py
server/database.py
server/decorators.py
server/main_window.py
server/remove_user.py
server/stat_window.py
ok_server_messenger-0.1.dist-info/METADATA
ok_server_messenger-0.1.dist-info/WHEEL
ok_server_messenger-0.1.dist-info/top_level.txt
ok_server_messenger-0.1.dist-info/RECORD
